{
  "entities": [
    {
      "id": "葉卅",
      "kind": "player",
      "display_char": "卅",
      "x": 0,
      "y": 0,
      "move_state": "idle",
      "vit": 10,
      "qi": 9,
      "dex": 12,
      "magnesium": 0,
      "created_at": 1772887195,
      "gender": "M",
      "soul_seed": 1186818334208741480,
      "activated_nodes": "[\"N000\"]",
      "equipment_slots": "{\"body\":\"starter_body_m\",\"legs\":\"starter_legs_m\",\"feet\":\"starter_feet_m\"}",
      "inventory": "[]"
    }
  ]
}